<annotation>
	<folder>images</folder>
	<filename>04.jpg</filename>
	<path>C:\Users\pc\Pictures\data\raw_data\images\04.jpg</path>
	<source>
		<database>Unknown</database>
	</source>
	<size>
		<width>2560</width>
		<height>2432</height>
		<depth>3</depth>
	</size>
	<segmented>0</segmented>
	<object>
		<name>sneakers</name>
		<pose>Unspecified</pose>
		<truncated>0</truncated>
		<difficult>0</difficult>
		<bndbox>
			<xmin>1013</xmin>
			<ymin>2268</ymin>
			<xmax>1103</xmax>
			<ymax>2373</ymax>
		</bndbox>
	</object>
	<object>
		<name>sneakers</name>
		<pose>Unspecified</pose>
		<truncated>0</truncated>
		<difficult>0</difficult>
		<bndbox>
			<xmin>1132</xmin>
			<ymin>2260</ymin>
			<xmax>1330</xmax>
			<ymax>2368</ymax>
		</bndbox>
	</object>
	<object>
		<name>sneakers</name>
		<pose>Unspecified</pose>
		<truncated>0</truncated>
		<difficult>0</difficult>
		<bndbox>
			<xmin>1551</xmin>
			<ymin>2243</ymin>
			<xmax>1646</xmax>
			<ymax>2365</ymax>
		</bndbox>
	</object>
	<object>
		<name>sneakers</name>
		<pose>Unspecified</pose>
		<truncated>0</truncated>
		<difficult>0</difficult>
		<bndbox>
			<xmin>1313</xmin>
			<ymin>2222</ymin>
			<xmax>1424</xmax>
			<ymax>2338</ymax>
		</bndbox>
	</object>
</annotation>
